Workbook

Sheet 历史数据
A1: 指标 | B1: 披露项目 | C1: 期间 | D1: 金额（人民币元） | E1: 主体与范围 | F1: 来源及PDF页码
A2: 2025 revenue | B2: 2025年度营业总收入 | C2: 2025年度 | D2: 1.2846823e+11 | E2: 广东海大集团股份有限公司；合并口径 | F2: 2025 annual report p.97
A3: 2024 revenue | B3: 2024年度营业总收入 | C3: 2024年度比较 | D3: 1.1460106e+11 | E3: 广东海大集团股份有限公司；合并口径 | F3: 2025 annual report p.97
A4: 2025 cost | B4: 2025年度营业成本 | C4: 2025年度 | D4: 1.1519334e+11 | E4: 广东海大集团股份有限公司；合并口径 | F4: 2025 annual report p.97
A5: 2025 net income | B5: 2025年度净利润 | C5: 2025年度 | D5: 4.5453938e+09 | E5: 广东海大集团股份有限公司；合并口径 | F5: 2025 annual report p.98
A6: 2025 operating cash flow | B6: 经营活动产生的现金流量净额 | C6: 2025年度 | D6: 6.2603773e+09 | E6: 广东海大集团股份有限公司；合并口径 | F6: 2025 annual report p.100
A7: 2025 investing cash flow | B7: 投资活动产生的现金流量净额 | C7: 2025年度 | D7: -1.3416114e+09 | E7: 广东海大集团股份有限公司；合并口径 | F7: 2025 annual report p.101
A8: 2025 financing cash flow | B8: 筹资活动产生的现金流量净额 | C8: 2025年度 | D8: -5.1758998e+09 | E8: 广东海大集团股份有限公司；合并口径 | F8: 2025 annual report p.101
A9: 2025 cash | B9: 货币资金及现金等价物 | C9: 2025-12-31 | D9: 3.2028363e+09 | E9: 广东海大集团股份有限公司；合并口径 | F9: 2025 annual report p.92-93
A10: 2025 receivables | B10: 应收账款 | C10: 2025-12-31 | D10: 2.9787632e+09 | E10: 广东海大集团股份有限公司；合并口径 | F10: 2025 annual report p.92
A11: 2025 inventory | B11: 存货 | C11: 2025-12-31 | D11: 1.1371777e+10 | E11: 广东海大集团股份有限公司；合并口径 | F11: 2025 annual report p.92
A12: 2025 payables | B12: 应付账款 | C12: 2025-12-31 | D12: 5.7260474e+09 | E12: 广东海大集团股份有限公司；合并口径 | F12: 2025 annual report p.94
A13: 2025 fixed assets | B13: 固定资产 | C13: 2025-12-31 | D13: 1.7007957e+10 | E13: 广东海大集团股份有限公司；合并口径 | F13: 2025 annual report p.93
... A39: 2026H1 total equity | B39: 所有者权益合计 | C39: 2026-06-30 | D39: 2.5092818e+10 | E39: 广东海大集团股份有限公司；合并口径 | F39: 2026 half-year report p.57

Sheet 情景假设
A1: 参数 | B1: 数值 | C1: 单位/依据與性质
A2: H2收入增速 | B2: 0.04 | C2: 百分比；分析者情景，可编辑；非公司预算/指引
A3: 营业成本率 | B3: 0.90655132 | C3: H1披露营业成本/收入；情景基准
A4: 应收账款/收入 | B4: 0.084231551 | C4: H1期末余额/H1收入；简化情景基准
A5: 存货/收入 | B5: 0.21665494 | C5: H1期末余额/H1收入；简化情景基准
A6: 应付账款/成本 | B6: 0.12565706 | C6: H1期末余额/H1营业成本；简化情景基准
A7: 资本开支 | B7: 1.6926784e+09 | C7: 人民币元；H1现金流披露购建长期资产支出作为H2情景输入
A8: 折旧 | B8: 5.1509688e+08 | C8: 人民币元；H1披露固定资产折旧作为H2情景输入
A9: 净新增借款 | B9: 0 | C9: 人民币元；分析者情景参数，缺少逐笔融资计划
A10: 现金股利 | B10: 0 | C10: 人民币元；分析者情景参数，未假设未来分红
A11: 所得税率 | B11: 0.25 | C11: 比例；简化分析者情景参数
A12: 分析敏感性增速变动 | B12: 0.01 | C12: 百分点；对H2收入增速上调1个百分点

Sheet 营运资本
A1: 项目 | B1: H1期末实际 | C1: 驱动参数 | D1: H2情景期末 | E1: 余额变动
A2: 应收账款 | B2: 5.4110322e+09 | C2: =情景假设!B4 -> 0.084231551 | D2: =利润表!B2*C2 -> 5.6274734e+09 | E2: =D2-B2 -> 2.1644129e+08
A3: 存货 | B3: 1.3917907e+10 | C3: =情景假设!B5 -> 0.21665494 | D3: =利润表!B2*C3 -> 1.4474623e+10 | E3: =D3-B3 -> 5.5671627e+08
A4: 应付账款 | B4: 7.3178686e+09 | C4: =情景假设!B6 -> 0.12565706 | D4: =利润表!B3*C4 -> 7.6105834e+09 | E4: =D4-B4 -> 2.9271474e+08

Sheet 固定资产与债务
A1: 项目 | B1: 2026H1期末实际 | C1: H2增加/变动 | D1: H2期末情景 | E1: 滚动公式
A2: 固定资产净额 | B2: 1.6764113e+10 | C2: =情景假设!B7-情景假设!B8 -> 1.1775815e+09 | D2: =B2+C2 -> 1.7941695e+10 | E2: 期初+资本开支-折旧
A3: 借款合计 | B3: 3.8506705e+09 | C3: =情景假设!B9 -> 0 | D3: =B3+C3 -> 3.8506705e+09 | E3: 期初+净新增借款
A4: 短期借款 | B4: 3.6010332e+09 | C4: 0 | D4: =B4+C3 -> 3.6010332e+09 | E4: 净新增借款简化计入短期借款
A5: 长期借款 | B5: 2.4963731e+08 | C5: 0 | D5: =B5 -> 2.4963731e+08 | E5: H2情景不变

Sheet 利润表
A1: 项目 | B1: 2026H2分析情景
A2: 营业收入 | B2: =历史数据!D20*(1+情景假设!B2) -> 6.6809567e+10
A3: 营业成本 | B3: =B2*情景假设!B3 -> 6.0566301e+10
A4: 折旧费用 | B4: =情景假设!B8 -> 5.1509688e+08
A5: 税前简化利润 | B5: =B2-B3-B4 -> 5.728169e+09
A6: 所得税 | B6: =MAX(0,B5*情景假设!B11) -> 1.4320422e+09
A7: 净利润 | B7: =B5-B6 -> 4.2961267e+09

Sheet 现金流量表
A1: 项目 | B1: 2026H2分析情景
A2: 净利润 | B2: =利润表!B7 -> 4.2961267e+09
A3: 加：折旧 | B3: =利润表!B4 -> 5.1509688e+08
A4: 营运资本现金流影响 | B4: =-营运资本!E2-营运资本!E3+营运资本!E4 -> -4.8044281e+08
A5: 经营活动现金流净额（简化） | B5: =SUM(B2:B4) -> 4.3307808e+09
A6: 资本开支 | B6: =-情景假设!B7 -> -1.6926784e+09
A7: 净新增借款 | B7: =情景假设!B9 -> 0
A8: 支付股利 | B8: =-情景假设!B10 -> 0
A9: 现金净变动 | B9: =SUM(B5:B8) -> 2.6381024e+09
A10: 期初现金及现金等价物 | B10: 3.1350563e+09
A11: 期末现金及现金等价物 | B11: =B9+B10 -> 5.7731587e+09

Sheet 资产负债表
A1: 项目 | B1: 2026H2情景期末
A2: 现金 | B2: =现金流量表!B11 -> 5.7731587e+09
A3: 应收账款 | B3: =营运资本!D2 -> 5.6274734e+09
A4: 存货 | B4: =营运资本!D3 -> 1.4474623e+10
A5: 固定资产净额 | B5: =固定资产与债务!D2 -> 1.7941695e+10
A6: 其他资产（未逐项预测汇总） | B6: =历史数据!D37-历史数据!D29-历史数据!D30-历史数据!D31-历史数据!D33 -> 1.6062798e+10
A7: 资产总计 | B7: =SUM(B2:B6) -> 5.9879748e+10
A8: 应付账款 | B8: =营运资本!D4 -> 7.6105834e+09
A9: 借款合计 | B9: =固定资产与债务!D3 -> 3.8506705e+09
A10: 其他负债（未逐项预测汇总） | B10: =历史数据!D38-历史数据!D32-历史数据!D35-历史数据!D36 -> 1.9029549e+10
A11: 权益 | B11: =历史数据!D39+利润表!B7-情景假设!B10 -> 2.9388945e+10
A12: 负债和权益 | B12: =SUM(B8:B11) -> 5.9879748e+10
A13: 平衡差额（资产-负债及权益） | B13: =B7-B12 -> 0

Sheet 检查
A1: 检查项目 | B1: 计算结果 | C1: 通过标准/说明
A2: 2026H1现金滚动差额 | B2: =历史数据!D28+历史数据!D27-历史数据!D29 -> 0 | C2: 绝对值≤1元
A3: H2现金滚动差额 | B3: =现金流量表!B9+现金流量表!B10-现金流量表!B11 -> 0 | C3: 绝对值≤1元
A4: H2资产负债差额 | B4: =资产负债表!B13 -> 0 | C4: 绝对值≤1元；差额显示模型未建模项的滚动限制
A5: 借款滚动差额 | B5: =固定资产与债务!D3-固定资产与债务!B3-固定资产与债务!C3 -> 0 | C5: 绝对值≤1元
A6: 固定资产滚动差额 | B6: =固定资产与债务!D2-固定资产与债务!B2-固定资产与债务!C2 -> 0 | C6: 绝对值≤1元
A7: 权益滚动差额 | B7: =资产负债表!B11-历史数据!D39-利润表!B7+情景假设!B10 -> 0 | C7: 绝对值≤1元
A8: H2收入增速+1个百分点影响 | B8: =历史数据!D20*(1+情景假设!B2+情景假设!B12)-利润表!B2 -> 6.4239968e+08 | C8: 大于0；公式直接引用敏感性参数
A9: 联动说明 | B9: 收入驱动成本及应收/存货；成本驱动应付；资本开支和折旧滚动固定资产；净利润、营运资本变化、资本开支、借款与股利驱动现金；净利润及股利驱动权益。 | C9: 分析者情景；其他资产与负债暂按H1余额汇总，未逐项预测

Sheet 说明
A1: 主题 | B1: 内容
A2: 主体、期间与单位 | B2: 广东海大集团股份有限公司合并口径；人民币元。年报提供2025/2024年度数据；半年报提供2026H1及2025H1比较数据。流量为对应期间发生额，资产负债项目为期末余额。
A3: 历史来源 | B3: 每项历史事实均列出报告名及PDF显示页码；引用页码采用报告印刷页码。年报与半年报期末数按各自披露口径记录。
A4: 情景假设 | B4: H2增速、资本开支、折旧、借款、股利和税率是可编辑分析参数，非公司预算、指引或批准计划。成本率与营运资本比例以H1披露数据作为简化基准。
A5: 三表联动 | B5: H2利润表、营运资本、固定资产、债务、现金和权益支持表以公式连接。H2现金流采用简化间接法；未逐项建模的经营、投资、融资及综合收益事项会影响预测精度。
A6: 模型限制 | B6: 公开资料未提供既有模型、批准预算、逐笔债务或获批资本开支计划；H2现金流为简化间接法，其他资产与其他负债先按H1汇总余额持平。该处理仅用于明确展示预测联动和滚动差额，不代表完整资产负债预测或经营计划。
B7: H2情景结果：期末现金约5773158712.02元；期末权益约29388944545.86元；资产负债差额0.00元；增速敏感性收入影响642399679.63元。检查差额保留用于识别其他资产/负债简化持平的局限。
